<?xml version="1.0"?>
<!DOCTYPE hibernate-mapping PUBLIC "-//Hibernate/Hibernate Mapping DTD 3.0//EN"
"http://hibernate.sourceforge.net/hibernate-mapping-3.0.dtd">
<!-- 
    Mapping file autogenerated by MyEclipse - Hibernate Tools
-->
<hibernate-mapping>
    <class name="com.kingstargroup.mobileMessage.hibernate.RCmMessages" table="R_CM_MESSAGES" schema="YKT_CUR">
         <id name="id" type="integer">
            <column name="ID" />
            <generator class="native" />
        </id>
         <property name="RDate" type="date">
            <column name="R_DATE" length="10" not-null="true" />
        </property>
        <property name="RTime" type="time">
            <column name="R_TIME" length="8" not-null="true" />
        </property>
        <property name="RCardId" type="string">
            <column name="R_Cardid" not-null="true" />
        </property>
        <property name="RObject" type="string">
            <column name="R_OBJECT" length="30" not-null="true" />
        </property>
        <property name="RContent" type="string">
            <column name="R_CONTENT" length="120" not-null="true" />
        </property>
     
        <property name="RPro" type="integer">
            <column name="R_PRO" not-null="true" />
        </property>
       
    </class>
</hibernate-mapping>
