<?xml version="1.0" encoding="utf-8"?>
<!DOCTYPE hibernate-mapping PUBLIC "-//Hibernate/Hibernate Mapping DTD 3.0//EN"
"http://hibernate.sourceforge.net/hibernate-mapping-3.0.dtd">
<!-- 
    Mapping file autogenerated by MyEclipse Persistence Tools
-->
<hibernate-mapping package="org.king.monitor.domain" schema="YKT_MON">
    <class name="MapStateDic" table="MAP_STATE_DIC">
        <id name="id" type="long">
            <column name="ID" precision="22" scale="0" />
            <generator class="increment"></generator>
        </id>
        <property name="stateid" type="string">
            <column name="STATEID" length="20" />
        </property>
        <property name="statename" type="string">
            <column name="STATENAME" length="60" />
        </property>
        <property name="tagcode" type="string">
            <column name="TAGCODE" length="30" />
        </property>
        <property name="showcolor" type="long">
            <column name="SHOWCOLOR" precision="22" scale="0" />
        </property>
        <property name="errornot" type="long">
            <column name="ERRORNOT" precision="22" scale="0" />
        </property>
        <property name="errorcode" type="string">
            <column name="ERRORCODE" length="25" />
        </property>
    </class>
</hibernate-mapping>
