<?xml version="1.0" encoding="utf-8"?>
<!DOCTYPE hibernate-mapping PUBLIC "-//Hibernate/Hibernate Mapping DTD 3.0//EN"
"http://hibernate.sourceforge.net/hibernate-mapping-3.0.dtd">
<!-- 
    Mapping file autogenerated by MyEclipse Persistence Tools
-->
<hibernate-mapping package="org.king.host.domain" schema="YKT_MON">
    <class name="MonitorHostscheduleddowntime" table="MONITOR_HOSTSCHEDULEDDOWNTIME" >
        <id name="scheduleddowntimeId" type="java.lang.Integer">
            <column name="SCHEDULEDDOWNTIME_ID" precision="22" scale="0" />
            <generator class="increment"></generator>
        </id>
        <property name="downtimeType" type="java.lang.Integer">
            <column name="DOWNTIME_TYPE" precision="22" scale="0" />
        </property>
        <property name="hostId" type="java.lang.Integer">
            <column name="HOST_ID" precision="22" scale="0" />
        </property>
        <property name="entryTime" type="java.lang.String">
            <column name="ENTRY_TIME"  />
        </property>
        <property name="authorName" type="java.lang.String">
            <column name="AUTHOR_NAME" length="64" />
        </property>
        <property name="commentData" type="java.lang.String">
            <column name="COMMENT_DATA" />
        </property>
        <property name="isFixed" type="java.lang.Integer">
            <column name="IS_FIXED" precision="22" scale="0" />
        </property>
        <property name="duration" type="java.lang.Integer">
            <column name="DURATION" precision="22" scale="0" />
        </property>
        <property name="scheduledStartTime" type="java.lang.String">
            <column name="SCHEDULED_START_TIME"  />
        </property>
        <property name="scheduledEndTime" type="java.lang.String">
            <column name="SCHEDULED_END_TIME"  />
        </property>
        <property name="wasStarted" type="java.lang.Integer">
            <column name="WAS_STARTED" precision="22" scale="0" />
        </property>
        <property name="actualStartTime" type="java.lang.String">
            <column name="ACTUAL_START_TIME"  />
        </property>
        <property name="actualEndTime" type="java.lang.String">
            <column name="ACTUAL_END_TIME"  />
        </property>
        <property name="wasCancelled" type="java.lang.Integer">
            <column name="WAS_CANCELLED" precision="22" scale="0" />
        </property>
    </class>
</hibernate-mapping>
