<?xml version="1.0" encoding="UTF-8"?>
<!DOCTYPE hibernate-mapping PUBLIC "-//Hibernate/Hibernate Mapping DTD 3.0//EN" "http://hibernate.sourceforge.net/hibernate-mapping-3.0.dtd">

<hibernate-mapping schema="ykt_portal">	   
    <!-- tables reference from "ykt_cur" schema -->
      <class name="com.kingstargroup.ecard.hibernate.card.TDept" table="T_DEPT" schema="ykt_cur">
        <id name="deptcode" type="java.lang.String">
            <column name="DEPTCODE" length="30" />
            <generator class="assigned"></generator>
        </id>
        <property name="areacode" type="java.lang.String">
            <column name="AREACODE" length="2" />
        </property>
        <property name="deptname" type="java.lang.String">
            <column name="DEPTNAME" length="240" />
        </property>
        <property name="deptename" type="java.lang.String">
            <column name="DEPTENAME" length="240" />
        </property>
        <property name="deptfullname" type="java.lang.String">
            <column name="DEPTFULLNAME" length="1000" />
        </property>
        <property name="fdeptcode" type="java.lang.String">
            <column name="FDEPTCODE" length="30" />
        </property>
        <property name="deptlevel" type="java.lang.Long">
            <column name="DEPTLEVEL" precision="22" scale="0" />
        </property>
        <property name="olddeptcode" type="java.lang.String">
            <column name="OLDDEPTCODE" length="30" />
        </property>
        <property name="useflag" type="java.lang.String">
            <column name="USEFLAG" length="1" />
        </property>
        <property name="lastsaved" type="java.lang.String">
            <column name="LASTSAVED" length="30" />
        </property>
    </class>
  <class name="com.kingstargroup.ecard.hibernate.custype.TCusttype" table="T_CUSTTYPE" schema="YKT_CUR">
        <id name="custtype" type="java.lang.Long">
            <column name="CUSTTYPE" precision="22" scale="0" />
            <generator class="assigned"></generator>
        </id>
        <property name="custtypename" type="java.lang.String">
            <column name="CUSTTYPENAME" length="60" />
        </property>
        <property name="feetype" type="java.lang.Long">
            <column name="FEETYPE" precision="22" scale="0" />
        </property>
        <property name="useflag" type="java.lang.String">
            <column name="USEFLAG" length="1" />
        </property>
    </class>
    
    <class name="com.kingstargroup.ecard.hibernate.photo.TPhoto" table="T_PHOTO" schema="YKT_CUR">
        <id name="custid" type="java.lang.Long">
            <column name="CUSTID" precision="22" scale="0" />
            <generator class="assigned"></generator>
        </id>
        <property name="stuempno" type="java.lang.String">
            <column name="STUEMPNO" length="30" />
        </property>
        <property name="photo" type="blob">
            <column name="PHOTO" />
        </property>
        <property name="photodate" type="java.lang.String">
            <column name="PHOTODATE" length="8" />
        </property>
        <property name="phototime" type="java.lang.String">
            <column name="PHOTOTIME" length="6" />
        </property>
        <property name="ifcard" type="java.lang.String">
            <column name="IFCARD" length="1" />
        </property>
        <property name="makecarddate" type="java.lang.String">
            <column name="MAKECARDDATE" length="8" />
        </property>
        <property name="makecardtime" type="java.lang.String">
            <column name="MAKECARDTIME" length="6" />
        </property>
        <property name="photoexacttime" type="java.lang.String">
            <column name="PHOTOEXACTTIME" length="30" />
        </property>
    </class>
    
    <class name="com.kingstargroup.ecard.hibernate.card.TSyspara" table="T_SYSPARA" schema="YKT_CUR">
        <id name="paraid" type="java.lang.Long">
            <column name="PARAID" precision="22" scale="0" />
            <generator class="assigned"></generator>
        </id>
        <property name="paraval" type="java.lang.String">
            <column name="PARAVAL" length="60" />
        </property>
        <property name="paraname" type="java.lang.String">
            <column name="PARANAME" length="60" />
        </property>
        <property name="paraunit" type="java.lang.String">
            <column name="PARAUNIT" length="30" />
        </property>
        <property name="displayflag" type="java.lang.String">
            <column name="DISPLAYFLAG" length="1" />
        </property>
        <property name="remark" type="java.lang.String">
            <column name="REMARK" length="240" />
        </property>
        <property name="lastsaved" type="java.lang.String">
            <column name="LASTSAVED" length="30" />
        </property>
    </class>
    
   <class name="com.kingstargroup.ecard.hibernate.card.TPosdtl" table="T_POSDTL" schema="YKT_CUR">
        <composite-id name="id" class="com.kingstargroup.ecard.hibernate.card.TPosdtlId">
            <key-property name="transdate" type="java.lang.String">
                <column name="TRANSDATE" length="8" />
            </key-property>
            <key-property name="devphyid" type="java.lang.String">
                <column name="DEVPHYID" length="30" />
            </key-property>
            <key-property name="devseqno" type="java.lang.Long">
                <column name="DEVSEQNO" precision="22" scale="0" />
            </key-property>
        </composite-id>
        <property name="transtime" type="java.lang.String">
            <column name="TRANSTIME" length="6" />
        </property>
        <property name="cardno" type="java.lang.Long">
            <column name="CARDNO" precision="22" scale="0" />
        </property>
        <property name="purseno" type="java.lang.Long">
            <column name="PURSENO" precision="22" scale="0" />
        </property>
        <property name="cardcnt" type="java.lang.Long">
            <column name="CARDCNT" precision="22" scale="0" />
        </property>
        <property name="cardbefbal" type="java.lang.Double">
            <column name="CARDBEFBAL" precision="15" />
        </property>
        <property name="amount" type="java.lang.Double">
            <column name="AMOUNT" precision="15" />
        </property>
        <property name="cardaftbal" type="java.lang.Double">
            <column name="CARDAFTBAL" precision="15" />
        </property>
        <property name="managefee" type="java.lang.Double">
            <column name="MANAGEFEE" precision="15" />
        </property>
        <property name="transmark" type="java.lang.Long">
            <column name="TRANSMARK" precision="22" scale="0" />
        </property>
        <property name="transcode" type="java.lang.Long">
            <column name="TRANSCODE" precision="22" scale="0" />
        </property>
        <property name="shopid" type="java.lang.Long">
            <column name="SHOPID" precision="22" scale="0" />
        </property>
        <property name="subsidyno" type="java.lang.Long">
            <column name="SUBSIDYNO" precision="22" scale="0" />
        </property>
        <property name="batchno" type="java.lang.String">
            <column name="BATCHNO" length="30" />
        </property>
        <property name="sysid" type="java.lang.Long">
            <column name="SYSID" precision="22" scale="0" />
        </property>
        <property name="coldate" type="java.lang.String">
            <column name="COLDATE" length="8" />
        </property>
        <property name="coltime" type="java.lang.String">
            <column name="COLTIME" length="6" />
        </property>
        <property name="accdate" type="java.lang.String">
            <column name="ACCDATE" length="8" />
        </property>
        <property name="acctime" type="java.lang.String">
            <column name="ACCTIME" length="6" />
        </property>
        <property name="termid" type="java.lang.Long">
            <column name="TERMID" precision="22" scale="0" />
        </property>
        <property name="termseqno" type="java.lang.Long">
            <column name="TERMSEQNO" precision="22" scale="0" />
        </property>
        <property name="status" type="java.lang.String">
            <column name="STATUS" length="1" not-null="true" />
        </property>
        <property name="errcode" type="java.lang.Long">
            <column name="ERRCODE" precision="22" scale="0" />
        </property>
        <property name="errmsg" type="java.lang.String">
            <column name="ERRMSG" length="240" />
        </property>
        <property name="delflag" type="java.lang.String">
            <column name="DELFLAG" length="1" />
        </property>
    </class>
        
    <class name="com.kingstargroup.ecard.hibernate.card.TMsglist" table="T_MSGLIST" schema="YKT_CUR">
        <id name="msgid" type="java.lang.Long">
            <column name="MSGID" precision="22" scale="0" />
             <generator class="sequence">
                <param name="sequence">YKT_CUR.S_T_TIF_MESLIST</param>
            </generator>
        </id>
        <property name="msgtype" type="java.lang.Long">
            <column name="MSGTYPE" precision="22" scale="0" />
        </property>
        <property name="msglevel" type="java.lang.Long">
            <column name="MSGLEVEL" precision="22" scale="0" />
        </property>
        <property name="sysid" type="java.lang.Long">
            <column name="SYSID" precision="22" scale="0" />
        </property>
        <property name="deviceid" type="java.lang.Long">
            <column name="DEVICEID" precision="22" scale="0" />
        </property>
        <property name="cardno" type="java.lang.Long">
            <column name="CARDNO" precision="22" scale="0" />
        </property>
        <property name="transdate" type="java.lang.String">
            <column name="TRANSDATE" length="8" />
        </property>
        <property name="createdtime" type="java.lang.String">
            <column name="CREATEDTIME" length="30" />
        </property>
        <property name="starttime" type="java.lang.String">
            <column name="STARTTIME" length="30" />
        </property>
        <property name="endtime" type="java.lang.String">
            <column name="ENDTIME" length="30" />
        </property>
        <property name="reqdata" type="java.lang.String">
            <column name="REQDATA" length="1000" />
        </property>
        <property name="respdata" type="java.lang.String">
            <column name="RESPDATA" length="1000" />
        </property>
        <property name="funcno" type="java.lang.Long">
            <column name="FUNCNO" precision="22" scale="0" />
        </property>
        <property name="pfuncno" type="java.lang.Long">
            <column name="PFUNCNO" precision="22" scale="0" />
        </property>
        <property name="maxsendcnt" type="java.lang.Long">
            <column name="MAXSENDCNT" precision="22" scale="0" />
        </property>
        <property name="sendcnt" type="java.lang.Long">
            <column name="SENDCNT" precision="22" scale="0" />
        </property>
        <property name="recvcnt" type="java.lang.Long">
            <column name="RECVCNT" precision="22" scale="0" />
        </property>
        <property name="status" type="java.lang.String">
            <column name="STATUS" length="1" />
        </property>
        <property name="seqno" type="java.lang.Long">
            <column name="SEQNO" precision="22" scale="0" />
        </property>
        <property name="opercode" type="java.lang.String">
            <column name="OPERCODE" length="8" />
        </property>
        <property name="errcode" type="java.lang.Long">
            <column name="ERRCODE" precision="22" scale="0" />
        </property>
        <property name="errmsg" type="java.lang.String">
            <column name="ERRMSG" length="240" />
        </property>
        <property name="delflag" type="java.lang.String">
            <column name="DELFLAG" length="1" />
        </property>
    </class>
    <class name="com.kingstargroup.ecard.hibernate.card.TSyskey" table="T_SYSKEY" schema="YKT_CUR">
        <id name="keycode" type="java.lang.String">
            <column name="KEYCODE" length="60" />
            <generator class="assigned"></generator>
        </id>
        <property name="keyname" type="java.lang.String">
            <column name="KEYNAME" length="60" />
        </property>
        <property name="keyval" type="java.lang.Double">
            <column name="KEYVAL" precision="15" />
        </property>
        <property name="maxval" type="java.lang.Long">
            <column name="MAXVAL" precision="22" scale="0" />
        </property>
        <property name="keytype" type="java.lang.String">
            <column name="KEYTYPE" length="1" />
        </property>
    </class>    
	
     <class name="com.kingstargroup.ecard.hibernate.card.TSubsystem" table="T_SUBSYSTEM" schema="YKT_CUR">
        <id name="sysid" type="java.lang.Long">
            <column name="SYSID" precision="22" scale="0" />
            <generator class="assigned"></generator>
        </id>
        <property name="sysname" type="java.lang.String">
            <column name="SYSNAME" length="60" />
        </property>
        <property name="systype" type="java.lang.Long">
            <column name="SYSTYPE" precision="22" scale="0" />
        </property>
        <property name="areacode" type="java.lang.String">
            <column name="AREACODE" length="3" />
        </property>
        <property name="serverid" type="java.lang.Long">
            <column name="SERVERID" precision="22" scale="0" />
        </property>
        <property name="macaddr" type="java.lang.String">
            <column name="MACADDR" length="17" />
        </property>
        <property name="ip" type="java.lang.String">
            <column name="IP" length="15" />
        </property>
        <property name="port" type="java.lang.Long">
            <column name="PORT" precision="22" scale="0" />
        </property>
        <property name="cardverno" type="java.lang.String">
            <column name="CARDVERNO" length="30" />
        </property>
        <property name="initkey" type="java.lang.String">
            <column name="INITKEY" length="32" />
        </property>
        <property name="dynakey" type="java.lang.String">
            <column name="DYNAKEY" length="32" />
        </property>
        <property name="synctime" type="java.lang.String">
            <column name="SYNCTIME" length="30" />
        </property>
        <property name="runstatus" type="java.lang.String">
            <column name="RUNSTATUS" length="1" />
        </property>
        <property name="status" type="java.lang.String">
            <column name="STATUS" length="1" />
        </property>
        <property name="opendate" type="java.lang.String">
            <column name="OPENDATE" length="8" />
        </property>
        <property name="closedate" type="java.lang.String">
            <column name="CLOSEDATE" length="8" />
        </property>
        <property name="remark" type="java.lang.String">
            <column name="REMARK" length="240" />
        </property>
    </class>
      <class name="com.kingstargroup.ecard.hibernate.card.TCardtype" table="T_CARDTYPE" schema="YKT_CUR">
        <id name="cardtype" type="java.lang.Long">
            <column name="CARDTYPE" precision="22" scale="0" />
            <generator class="assigned"></generator>
        </id>
        <property name="cardtypename" type="java.lang.String">
            <column name="CARDTYPENAME" length="60" />
        </property>
        <property name="anonymflag" type="java.lang.String">
            <column name="ANONYMFLAG" length="1" />
        </property>
        <property name="feetype" type="java.lang.Long">
            <column name="FEETYPE" precision="22" scale="0" />
        </property>
        <property name="cardcostfee" type="java.lang.Double">
            <column name="CARDCOSTFEE" precision="15" />
        </property>
        <property name="reuseable" type="java.lang.String">
            <column name="REUSEABLE" length="1" />
        </property>
        <property name="renewable" type="java.lang.String">
            <column name="RENEWABLE" length="1" />
        </property>
        <property name="multipurse" type="java.lang.String">
            <column name="MULTIPURSE" length="1" />
        </property>
        <property name="fixdayflag" type="java.lang.String">
            <column name="FIXDAYFLAG" length="1" />
        </property>
        <property name="fixdaycnt" type="java.lang.Long">
            <column name="FIXDAYCNT" precision="22" scale="0" />
        </property>
        <property name="useflag" type="java.lang.String">
            <column name="USEFLAG" length="1" />
        </property>
        <property name="purpose" type="java.lang.String">
            <column name="PURPOSE" length="240" />
        </property>
    </class>
    
	 <class name="com.kingstargroup.ecard.hibernate.card.TCardver" table="T_CARDVER" schema="YKT_CUR">
        <id name="cardverno" type="java.lang.String">
            <column name="CARDVERNO" length="30" />
            <generator class="assigned"></generator>
        </id>
        <property name="accdate" type="java.lang.String">
            <column name="ACCDATE" length="8" />
        </property>
        <property name="termid" type="java.lang.Long">
            <column name="TERMID" precision="22" scale="0" />
        </property>
        <property name="termseqno" type="java.lang.Long">
            <column name="TERMSEQNO" precision="22" scale="0" />
        </property>
        <property name="cardno" type="java.lang.Long">
            <column name="CARDNO" precision="22" scale="0" />
        </property>
        <property name="cardphyid" type="java.lang.String">
            <column name="CARDPHYID" length="8" />
        </property>
        <property name="stuempno" type="java.lang.String">
            <column name="STUEMPNO" length="30" />
        </property>
        <property name="cardvertype" type="java.lang.Long">
            <column name="CARDVERTYPE" precision="22" scale="0" />
        </property>
        <property name="adddelflag" type="java.lang.String">
            <column name="ADDDELFLAG" length="1" />
        </property>
        <property name="status" type="java.lang.String">
            <column name="STATUS" length="1" />
        </property>
    </class>
    
 <class name="com.kingstargroup.ecard.hibernate.customer.TCustomer" table="T_CUSTOMER" schema="YKT_CUR">
        <id name="custid" type="java.lang.Long">
            <column name="CUSTID" precision="22" scale="0" />
            <generator class="assigned"></generator>
        </id>
        <property name="stuempno" type="java.lang.String">
            <column name="STUEMPNO" length="30" />
        </property>
        <property name="custtype" type="java.lang.Long">
            <column name="CUSTTYPE" precision="22" scale="0" />
        </property>
        <property name="feetype" type="java.lang.Long">
            <column name="FEETYPE" precision="22" scale="0" />
        </property>
        <property name="status" type="java.lang.String">
            <column name="STATUS" length="1" />
        </property>
        <property name="custname" type="java.lang.String">
            <column name="CUSTNAME" length="60" />
        </property>
        <property name="areacode" type="java.lang.String">
            <column name="AREACODE" length="3" />
        </property>
        <property name="deptcode" type="java.lang.String">
            <column name="DEPTCODE" length="30" />
        </property>
        <property name="deptfullname" type="java.lang.String">
            <column name="DEPTFULLNAME" length="1000" />
        </property>
        <property name="specialtycode" type="java.lang.String">
            <column name="SPECIALTYCODE" length="30" />
        </property>
        <property name="classcode" type="java.lang.String">
            <column name="CLASSCODE" length="30" />
        </property>
        <property name="idtype" type="java.lang.String">
            <column name="IDTYPE" length="1" />
        </property>
        <property name="idno" type="java.lang.String">
            <column name="IDNO" length="60" />
        </property>
        <property name="sex" type="java.lang.String">
            <column name="SEX" length="1" />
        </property>
        <property name="country" type="java.lang.String">
            <column name="COUNTRY" length="3" />
        </property>
        <property name="nation" type="java.lang.String">
            <column name="NATION" length="2" />
        </property>
        <property name="email" type="java.lang.String">
            <column name="EMAIL" length="60" />
        </property>
        <property name="tel" type="java.lang.String">
            <column name="TEL" length="30" />
        </property>
        <property name="mobile" type="java.lang.String">
            <column name="MOBILE" length="30" />
        </property>
        <property name="addr" type="java.lang.String">
            <column name="ADDR" length="240" />
        </property>
        <property name="zipcode" type="java.lang.String">
            <column name="ZIPCODE" length="6" />
        </property>
        <property name="custattr" type="java.lang.String">
            <column name="CUSTATTR" length="10" />
        </property>
        <property name="indate" type="java.lang.String">
            <column name="INDATE" length="8" />
        </property>
        <property name="outdate" type="java.lang.String">
            <column name="OUTDATE" length="8" />
        </property>
        <property name="opendate" type="java.lang.String">
            <column name="OPENDATE" length="8" />
        </property>
        <property name="closedate" type="java.lang.String">
            <column name="CLOSEDATE" length="8" />
        </property>
        <property name="batchno" type="java.lang.String">
            <column name="BATCHNO" length="30" />
        </property>
        <property name="holdcardcnt" type="java.lang.Long">
            <column name="HOLDCARDCNT" precision="22" scale="0" />
        </property>
        <property name="useflag" type="java.lang.String">
            <column name="USEFLAG" length="1" />
        </property>
        <property name="eaccflag" type="java.lang.String">
            <column name="EACCFLAG" length="1" />
        </property>
        <property name="lastsaved" type="java.lang.String">
            <column name="LASTSAVED" length="30" />
        </property>
    </class>
  <class name="com.kingstargroup.ecard.hibernate.account.TAccount" table="T_ACCOUNT" schema="YKT_CUR">
        <id name="accno" type="java.lang.String">
            <column name="ACCNO" length="20" />
            <generator class="assigned"></generator>
        </id>
        <property name="acctype" type="java.lang.Long">
            <column name="ACCTYPE" precision="22" scale="0" />
        </property>
        <property name="accname" type="java.lang.String">
            <column name="ACCNAME" />
        </property>
        <property name="subjno" type="java.lang.String">
            <column name="SUBJNO" length="20" />
        </property>
        <property name="accpwd" type="java.lang.String">
            <column name="ACCPWD" length="32" />
        </property>
        <property name="custid" type="java.lang.Long">
            <column name="CUSTID" precision="22" scale="0" />
        </property>
        <property name="cardno" type="java.lang.Long">
            <column name="CARDNO" precision="22" scale="0" />
        </property>
        <property name="purseno" type="java.lang.Long">
            <column name="PURSENO" precision="22" scale="0" />
        </property>
        <property name="daycostmaxamt" type="java.lang.Double">
            <column name="DAYCOSTMAXAMT" precision="15" />
        </property>
        <property name="cardmaxbal" type="java.lang.Double">
            <column name="CARDMAXBAL" precision="15" />
        </property>
        <property name="stoppayflag" type="java.lang.String">
            <column name="STOPPAYFLAG" length="1" />
        </property>
        <property name="status" type="java.lang.String">
            <column name="STATUS" length="1" />
        </property>
        <property name="ydaybal" type="java.lang.Double">
            <column name="YDAYBAL" precision="15" />
        </property>
        <property name="ydayavailbal" type="java.lang.Double">
            <column name="YDAYAVAILBAL" precision="15" />
        </property>
        <property name="ydayfrozebal" type="java.lang.Double">
            <column name="YDAYFROZEBAL" precision="15" />
        </property>
        <property name="balance" type="java.lang.Double">
            <column name="BALANCE" precision="15" />
        </property>
        <property name="availbal" type="java.lang.Double">
            <column name="AVAILBAL" precision="15" />
        </property>
        <property name="frozebal" type="java.lang.Double">
            <column name="FROZEBAL" precision="15" />
        </property>
        <property name="subsidybal" type="java.lang.Double">
            <column name="SUBSIDYBAL" precision="15" />
        </property>
        <property name="foregift" type="java.lang.Double">
            <column name="FOREGIFT" precision="15" />
        </property>
        <property name="lastcardcnt" type="java.lang.Long">
            <column name="LASTCARDCNT" precision="22" scale="0" />
        </property>
        <property name="lastcardbal" type="java.lang.Double">
            <column name="LASTCARDBAL" precision="15" />
        </property>
        <property name="subsidyno" type="java.lang.Long">
            <column name="SUBSIDYNO" precision="22" scale="0" />
        </property>
        <property name="lastsubsidyno" type="java.lang.Long">
            <column name="LASTSUBSIDYNO" precision="22" scale="0" />
        </property>
        <property name="daycostamt" type="java.lang.Double">
            <column name="DAYCOSTAMT" precision="15" />
        </property>
        <property name="lasttransdate" type="java.lang.String">
            <column name="LASTTRANSDATE" length="8" />
        </property>
        <property name="lastaccdate" type="java.lang.String">
            <column name="LASTACCDATE" length="8" />
        </property>
        <property name="opendate" type="java.lang.String">
            <column name="OPENDATE" length="8" />
        </property>
        <property name="closedate" type="java.lang.String">
            <column name="CLOSEDATE" length="8" />
        </property>
        <property name="singlemaxamt" type="java.lang.Double">
            <column name="SINGLEMAXAMT" precision="15" />
        </property>
    </class>
    
     <class name="com.kingstargroup.ecard.hibernate.card.TCard" table="T_CARD" schema="YKT_CUR">
        <id name="cardno" type="java.lang.Long">
            <column name="CARDNO" precision="22" scale="0" />
            <generator class="assigned"></generator>
        </id>
        <property name="cardtype" type="java.lang.Long">
            <column name="CARDTYPE" precision="22" scale="0" />
        </property>
        <property name="feetype" type="java.lang.Long">
            <column name="FEETYPE" precision="22" scale="0" />
        </property>
        <property name="custid" type="java.lang.Long">
            <column name="CUSTID" precision="22" scale="0" />
        </property>
        <property name="showcardno" type="java.lang.String">
            <column name="SHOWCARDNO" length="10" />
        </property>
        <property name="cardphyid" type="java.lang.String">
            <column name="CARDPHYID" length="8" />
        </property>
        <property name="cardpwd" type="java.lang.String">
            <column name="CARDPWD" length="32" />
        </property>
        <property name="expiredate" type="java.lang.String">
            <column name="EXPIREDATE" length="8" />
        </property>
        <property name="status" type="java.lang.String">
            <column name="STATUS" length="1" not-null="true" />
        </property>
        <property name="lossflag" type="java.lang.String">
            <column name="LOSSFLAG" length="1" not-null="true" />
        </property>
        <property name="lossdate" type="java.lang.String">
            <column name="LOSSDATE" length="8" />
        </property>
        <property name="lossefttime" type="java.lang.String">
            <column name="LOSSEFTTIME" length="30" />
        </property>
        <property name="frozeflag" type="java.lang.String">
            <column name="FROZEFLAG" length="1" not-null="true" />
        </property>
        <property name="frozedate" type="java.lang.String">
            <column name="FROZEDATE" length="8" />
        </property>
        <property name="badflag" type="java.lang.String">
            <column name="BADFLAG" length="1" not-null="true" />
        </property>
        <property name="badtype" type="java.lang.String">
            <column name="BADTYPE" length="1" />
        </property>
        <property name="baddate" type="java.lang.String">
            <column name="BADDATE" length="8" />
        </property>
        <property name="lockflag" type="java.lang.String">
            <column name="LOCKFLAG" length="1" />
        </property>
        <property name="lockdate" type="java.lang.String">
            <column name="LOCKDATE" length="8" />
        </property>
        <property name="opendate" type="java.lang.String">
            <column name="OPENDATE" length="8" />
        </property>
        <property name="closedate" type="java.lang.String">
            <column name="CLOSEDATE" length="8" />
        </property>
        <property name="lastsaved" type="java.lang.String">
            <column name="LASTSAVED" length="30" />
        </property>
    </class>
    

       <class name="com.kingstargroup.ecard.hibernate.dictionary.TDictionary" table="T_DICTIONARY" schema="YKT_CUR">
        <composite-id name="id" class="com.kingstargroup.ecard.hibernate.dictionary.TDictionaryId">
            <key-property name="dicttype" type="java.lang.Long">
                <column name="DICTTYPE" precision="22" scale="0" />
            </key-property>
            <key-property name="dictval" type="java.lang.String">
                <column name="DICTVAL" length="30" />
            </key-property>
        </composite-id>
        <property name="dicttypename" type="java.lang.String">
            <column name="DICTTYPENAME" length="60" />
        </property>
        <property name="dictcaption" type="java.lang.String">
            <column name="DICTCAPTION" length="60" />
        </property>
    </class>
   <class name="com.kingstargroup.ecard.hibernate.area.TArea" table="T_AREA" schema="YKT_CUR">
        <id name="areacode" type="java.lang.String">
            <column name="AREACODE" length="3" />
            <generator class="assigned"></generator>
        </id>
        <property name="areaname" type="java.lang.String">
            <column name="AREANAME" length="60" />
        </property>
        <property name="fareacode" type="java.lang.String">
            <column name="FAREACODE" length="3" />
        </property>
        <property name="arealevel" type="java.lang.Long">
            <column name="AREALEVEL" precision="22" scale="0" />
        </property>
        <property name="addr" type="java.lang.String">
            <column name="ADDR" length="240" />
        </property>
        <property name="remark" type="java.lang.String">
            <column name="REMARK" length="240" />
        </property>
    </class>
      <class name="com.kingstargroup.ecard.hibernate.device.TDevice" table="T_DEVICE" schema="YKT_CUR">
        <id name="deviceid" type="java.lang.Long">
            <column name="DEVICEID" precision="22" scale="0" />
            <generator class="assigned"></generator>
        </id>
        <property name="devicename" type="java.lang.String">
            <column name="DEVICENAME" length="60" />
        </property>
        <property name="devphyid" type="java.lang.String">
            <column name="DEVPHYID" length="30" />
        </property>
        <property name="deviceno" type="java.lang.Long">
            <column name="DEVICENO" precision="22" scale="0" />
        </property>
        <property name="devphytype" type="java.lang.Long">
            <column name="DEVPHYTYPE" precision="22" scale="0" />
        </property>
        <property name="devtypecode" type="java.lang.String">
            <column name="DEVTYPECODE" length="30" />
        </property>
        <property name="devverno" type="java.lang.String">
            <column name="DEVVERNO" length="30" />
        </property>
        <property name="cardphytype" type="java.lang.String">
            <column name="CARDPHYTYPE" length="2" />
        </property>
        <property name="fdeviceid" type="java.lang.Long">
            <column name="FDEVICEID" precision="22" scale="0" />
        </property>
        <property name="runstatus" type="java.lang.String">
            <column name="RUNSTATUS" length="1" />
        </property>
        <property name="status" type="java.lang.String">
            <column name="STATUS" length="1" />
        </property>
        <property name="svrportcnt" type="java.lang.Long">
            <column name="SVRPORTCNT" precision="22" scale="0" />
        </property>
        <property name="svrportno" type="java.lang.Long">
            <column name="SVRPORTNO" precision="22" scale="0" />
        </property>
        <property name="commtype" type="java.lang.Long">
            <column name="COMMTYPE" precision="22" scale="0" />
        </property>
        <property name="ip" type="java.lang.String">
            <column name="IP" length="15" />
        </property>
        <property name="portno" type="java.lang.Long">
            <column name="PORTNO" precision="22" scale="0" />
        </property>
        <property name="baudrate" type="java.lang.Long">
            <column name="BAUDRATE" precision="22" scale="0" />
        </property>
        <property name="cardset" type="java.lang.String">
            <column name="CARDSET" length="64" />
        </property>
        <property name="cardverno" type="java.lang.String">
            <column name="CARDVERNO" length="30" />
        </property>
        <property name="lastseqno" type="java.lang.Long">
            <column name="LASTSEQNO" precision="22" scale="0" />
        </property>
        <property name="lasttranstime" type="java.lang.String">
            <column name="LASTTRANSTIME" length="30" />
        </property>
        <property name="purseno" type="java.lang.Long">
            <column name="PURSENO" precision="22" scale="0" />
        </property>
        <property name="maxamt" type="java.lang.Double">
            <column name="MAXAMT" precision="15" />
        </property>
        <property name="sysid" type="java.lang.Long">
            <column name="SYSID" precision="22" scale="0" />
        </property>
        <property name="areacode" type="java.lang.String">
            <column name="AREACODE" length="3" />
        </property>
        <property name="doorlstver" type="java.lang.String">
            <column name="DOORLSTVER" length="30" />
        </property>
        <property name="devusage" type="java.lang.Long">
            <column name="DEVUSAGE" precision="22" scale="0" />
        </property>
        <property name="opendate" type="java.lang.String">
            <column name="OPENDATE" length="8" />
        </property>
        <property name="closedate" type="java.lang.String">
            <column name="CLOSEDATE" length="8" />
        </property>
        <property name="batchno" type="java.lang.String">
            <column name="BATCHNO" length="30" />
        </property>
        <property name="lastsaved" type="java.lang.String">
            <column name="LASTSAVED" length="30" />
        </property>
        <property name="remark" type="java.lang.String">
            <column name="REMARK" length="240" />
        </property>
    </class>
    
  <class name="com.kingstargroup.ecard.hibernate.tradecode.TTranscode" table="T_TRANSCODE" schema="YKT_CUR">
        <id name="transcode" type="java.lang.Long">
            <column name="TRANSCODE" precision="22" scale="0" />
            <generator class="assigned"></generator>
        </id>
        <property name="transname" type="java.lang.String">
            <column name="TRANSNAME" length="60" />
        </property>
        <property name="logflag" type="java.lang.Long">
            <column name="LOGFLAG" precision="22" scale="0" />
        </property>
        <property name="limitflag" type="java.lang.Long">
            <column name="LIMITFLAG" precision="22" scale="0" />
        </property>
        <property name="feeflag" type="java.lang.Long">
            <column name="FEEFLAG" precision="22" scale="0" />
        </property>
        <property name="transflag" type="java.lang.Long">
            <column name="TRANSFLAG" precision="22" scale="0" />
        </property>
        <property name="disableflag" type="java.lang.Long">
            <column name="DISABLEFLAG" precision="22" scale="0" />
        </property>
    </class>
  
    <!-- tables reference from "ykt_cur" schema end -->	
       
     <class name="com.kingstargroup.ecard.hibernate.information.EcardInformation" table="ECARD_INFORMATION">
     	<cache usage="read-write" />
        <id name="id" column="ID" type="integer">
            <generator class="increment"/>
        </id>
 
        <property name="infoType" column="INFO_TYPE" type="string" />
        <property name="infoTitle" column="INFO_TITLE" type="string" />
        <property name="infoContent" column="INFO_CONTENT" type="string" />
        <property name="attachments" column="ATTACHMENTS" type="string" />
        <property name="createDate" column="CREATE_DATE" type="timestamp" />
        <property name="creater" column="CREATER" type="string" />
    </class>
    
    <class name="com.kingstargroup.ecard.hibernate.upload.UploadFiles" table="UPLOAD_FILES">
	    <cache usage="read-write" />
        <id name="id" column="ID" type="integer">
            <generator class="increment"/>
        </id>
 
        <property name="storeFilename" column="STORE_FILENAME" type="string" />
        <property name="oldFilename" column="OLD_FILENAME" type="string" />
    </class>
        
    <class name="com.kingstargroup.ecard.hibernate.infotype.InfoType" table="INFO_TYPE">
    	<cache usage="read-write" />
        <id name="infoType" column="INFO_TYPE" type="string">
            <generator class="assigned"/>
        </id>
 
        <property name="infoName" column="INFO_NAME" type="string" />
    </class>
    
	<class name="com.kingstargroup.ecard.hibernate.postpone.EcardPostponeApply" table="ECARD_POSTPONE_APPLY">
        <id name="id" column="ID" type="integer">
            <generator class="increment"/>
        </id>
 
        <property name="stuempno" column="STUEMPNO" type="string" />
        <property name="reason" column="REASON" type="string" />
        <property name="postponeTime" column="POSTPONE_TIME" type="string" />
        <property name="applyTime" column="APPLY_TIME" type="timestamp" />
        <property name="checkResult" column="CHECK_RESULT" type="string" />
        <property name="status" column="STATUS" type="string" />
    </class>


    
    <class name="com.kingstargroup.ecard.hibernate.picdelay.EcardPicDelay" table="ECARD_PIC_DELAY">
        <id name="curStuempNo" column="CUR_STUEMP_NO" type="string">
            <generator class="assigned"/>
        </id>
 
        <property name="oldStuempNo" column="OLD_STUEMP_NO" type="string" />
        <property name="status" column="STATUS" type="string" />
    </class>
    
    <class name="com.kingstargroup.ecard.hibernate.picdelay.PostponeFiles" table="POSTPONE_FILES">
        <id name="id" column="ID" type="integer">
            <generator class="increment"/>
        </id>
 
        <property name="generateDate" column="GENERATE_DATE" type="timestamp" />
        <property name="fileContent" column="FILE_CONTENT" type="string" />
    </class>
    
	<class name="com.kingstargroup.ecard.hibernate.msgboard.EcardMsgboard" table="ECARD_MSGBOARD">
        <id name="id" column="ID" type="integer">
            <generator class="increment"/>
        </id>
 
        <property name="msgTitle" column="MSG_TITLE" type="string" />
        <property name="postTime" column="POST_TIME" type="timestamp" />
        <property name="poster" column="POSTER" type="string" />
        <property name="postContent" column="POST_CONTENT" type="string" />
        <property name="replyTime" column="REPLY_TIME" type="timestamp" />
        <property name="replyer" column="REPLYER" type="string" />
        <property name="replyContent" column="REPLY_CONTENT" type="string" />
        <property name="status" column="STATUS" type="string" />
    </class>
    
	<class name="com.kingstargroup.ecard.hibernate.hitinfo.EcardHitInfo" table="ECARD_HIT_INFO">
        <id name="id" column="ID" type="integer">
            <generator class="increment"/>
        </id>
 
        <property name="title" column="TITLE" type="string" />
        <property name="infoId" column="INFO_ID" type="integer"  not-null="true" />
    </class>
    
    
	
	<sql-query name="TradelogSQL">
		<return-scalar column="Serial_type" type="integer" />
		<return-scalar column="Device_Id" type="integer" />
		<return-scalar column="Operate_Date" type="string" />
		<return-scalar column="Operate_time" type="string" />
		<return-scalar column="Op_Fee" type="double" />
		<return-scalar column="out_balance" type="double" />
		<return-scalar column="trade_count" type="integer" />
		 select transcode as Serial_type,termid as Device_Id ,transdate as Operate_Date,transtime as Operate_time,
         (cardaftbal-cardbefbal) as Op_Fee,cardaftbal as out_balance,cardcnt as trade_count
         from ykt_cur.t_transdtl where transdate>=:startDate and not (transdate>:endDate) and
         cardno=:cardno and status='3' order by cardno desc,transdate desc,cardcnt desc
	</sql-query>
	
	   <sql-query name="TradelogCountSQL">
        <return-scalar column="count" type="integer" />
             select  count(*) count
                   from ykt_cur.t_transdtl where transdate>=:startDate and not (transdate>:endDate) and
                  cardno=:cardno and status='3'
    </sql-query>
	
	
	<!--门禁医院流水查询语句 -->	
	<sql-query name="GateHisTradelogSQL">
		<return-scalar column="DEVICE_ID" type="integer"/>
		<return-scalar column="DEVICE_NAME" type="string"/>
		<return-scalar column="TX_DATE" type="string"/>
		<return-scalar column="TX_TIME" type="string"/>
		<return-scalar column="CARD_NO" type="integer"/>
		<return-scalar column="TX_MARK" type="integer"/>
			select DEVICE_ID, DEVICE_NAME,TX_DATE, TX_TIME, CARD_NO, TX_MARK from(
			select dev.DEVICE_ID, dev.DEVICE_NAME,door.TX_DATE, door.TX_TIME, door.CARD_NO, door.TX_MARK
			from YKT_CUR.T_DOOR_TXDTL door,YKT_CUR.T_PIF_DEVICE dev 
			where door.device_id=dev.DEVICE_ID and tx_date>=:startDate and not(tx_date>:endDate) and card_no in (:cardNo)
			union all
			select dev.DEVICE_ID, dev.DEVICE_NAME,door.TX_DATE, door.TX_TIME, door.CARD_NO, door.TX_MARK
			from YKT_HIS.T_DOOR_TXDTL_HIS door,YKT_CUR.T_PIF_DEVICE dev 
			where door.device_id=dev.DEVICE_ID and tx_date>=:startDate and not(tx_date>:endDate) and card_no in (:cardNo)) t
			order by tx_date,tx_time
		
	</sql-query>
	
	<!--门禁医院流水查询语句 -->	
	<sql-query name="GateHisTradelogCountSQL">
		<return-scalar column="count" type="integer"/>
			select count(*) count from(
			select dev.DEVICE_ID, door.TX_DATE, door.TX_TIME, door.CARD_NO, door.TX_MARK
			from YKT_CUR.T_DOOR_TXDTL door,YKT_CUR.T_PIF_DEVICE dev 
			where door.device_id=dev.DEVICE_ID and tx_date>=:startDate and not(tx_date>:endDate) and card_no in (:cardNo)
			union all
			select dev.DEVICE_ID, door.TX_DATE, door.TX_TIME, door.CARD_NO, door.TX_MARK
			from YKT_HIS.T_DOOR_TXDTL_HIS door,YKT_CUR.T_PIF_DEVICE dev 
			where door.device_id=dev.DEVICE_ID and tx_date>=:startDate and not(tx_date>:endDate) and card_no in (:cardNo)) t
		
	</sql-query>	
	
	
	<sql-query name="CheckTTLogSQL">
		<return-scalar column="cust_id" type="integer"/>
		<return-scalar column="cut_name" type="string"/>
		<return-scalar column="stuemp_no" type="string"/>
		<return-scalar column="att_date" type="string"/>
		<return-scalar column="attnum" type="integer"/>
		select cust_id, cut_name,stuemp_no, att_date,count(*) attnum from(
		select att.cust_id, cust.cut_name,cust.stuemp_no, att.att_date
		from ykt_ck.t_attserial att left join ykt_cur.t_cif_customer cust on att.cust_id=cust.cut_id
		where cust.stuemp_no=:stuempNo and att.att_date>=:startDate and not (att.att_date>:endDate)
		union all
		select att.cust_id, cust.cut_name,cust.stuemp_no, att.att_date
		from ykt_ck.t_attserial_record att left join ykt_cur.t_cif_customer cust on att.cust_id=cust.cut_id
		where cust.stuemp_no=:stuempNo and att.att_date>=:startDate and not (att.att_date>:endDate)
		)t
		group by cust_id, cut_name,stuemp_no, att_date
		order by att_date
	</sql-query>
	
		<sql-query name="CheckTTLogCountSQL">
		<return-scalar column="count" type="integer"/>
		select count(*) count from(
		select cust_id, cut_name,stuemp_no, att_date,count(*) attnum from(
		select att.cust_id, cust.cut_name,cust.stuemp_no, att.att_date
		from ykt_ck.t_attserial att left join ykt_cur.t_cif_customer cust on att.cust_id=cust.cut_id
		where cust.stuemp_no=:stuempNo and att.att_date>=:startDate and not (att.att_date>:endDate)
		union all
		select att.cust_id, cust.cut_name,cust.stuemp_no, att.att_date
		from ykt_ck.t_attserial_record att left join ykt_cur.t_cif_customer cust on att.cust_id=cust.cut_id
		where cust.stuemp_no=:stuempNo and att.att_date>=:startDate and not (att.att_date>:endDate)
		)t
		group by cust_id, cut_name,stuemp_no, att_date
		order by att_date
		)s
	</sql-query>
	
	
	<sql-query name="TodayTradelogCountSQL">
		<return-scalar column="count" type="integer" />
			select count(*) count
			   from ykt_cur.t_tif_tradeserial log 
			    where log.operate_date>= :startDate and not(log.operate_date > :endDate) and 
			    log.card_id = :cardId and log.serial_state = 2
	</sql-query>
	
	<sql-query name="ErrorMsgSQL">
		<return-scalar column="EMSG" type="string" />
		select EMSG 
		from YKT_CUR.T_PIF_ERRCODE where substr(char(ECODE),1,2)='39' 
		and substr(char(ECODE),3,length(ECODE))=:code
	</sql-query>
</hibernate-mapping>