<?xml version="1.0"?>
<!DOCTYPE hibernate-mapping PUBLIC "-//Hibernate/Hibernate Mapping DTD 3.0//EN"
"http://hibernate.sourceforge.net/hibernate-mapping-3.0.dtd">
<!-- 
    Mapping file autogenerated by MyEclipse - Hibernate Tools
-->
<hibernate-mapping>
    <class name="org.king.checkinmanage.domain.Uploadfile" table="YX_UPLOADFILE" schema="YKT_FM">
        <id name="id" type="string">
            <column name="ID" length="32" />
            <generator class="uuid.hex" />
        </id>
        <many-to-one name="yxNotice" class="org.king.checkinmanage.domain.Noticemodel" fetch="select">
            <column name="NOTICE_ID" length="32" not-null="true" />
        </many-to-one>
        <property name="fileName" type="string">
            <column name="FILE_NAME" length="225" not-null="true" />
        </property>
        <property name="filePath" type="string">
            <column name="FILE_PATH" length="225" not-null="true" />
        </property>
        <property name="fileSize" type="string">
            <column name="FILE_SIZE" length="64" not-null="true" />
        </property>
        <property name="ifDeleted" type="string">
            <column name="IF_DELETED" length="1" not-null="true" />
        </property>
    </class>
</hibernate-mapping>
