<?xml version="1.0" encoding='UTF-8'?>
<!DOCTYPE hibernate-mapping PUBLIC
                            "-//Hibernate/Hibernate Mapping DTD 3.0//EN"
                            "http://hibernate.sourceforge.net/hibernate-mapping-3.0.dtd" >

<!-- DO NOT EDIT: This is a generated file that is synchronized -->
<!-- by MyEclipse Hibernate tool integration.                   -->
<!-- Created Mon Oct 10 15:35:03 CST 2005                         -->
<hibernate-mapping package="com.kingstargroup.form" schema="ykt_mon">

    <class name="MapContactTable" table="MAP_CONTACT_TABLE">
        <id name="id" column="ID" type="integer">
            <generator class="increment"/>
        </id>
 
        <property name="contactname" column="CONTACTNAME" type="string" />
        <property name="contactgender" column="CONTACTGENDER" type="string" />
        <property name="contactcompany" column="CONTACTCOMPANY" type="string" />
        <property name="weekdays" column="WEEKDAYS" type="string" />
        <property name="starttime" column="STARTTIME" type="string" />
        <property name="endtime" column="ENDTIME" type="string" />
        <property name="email" column="EMAIL" type="string" />
        <property name="cellphone" column="CELLPHONE" type="string" />
    </class>
    
</hibernate-mapping>
