<?xml version="1.0" encoding="UTF-8"?>

<!DOCTYPE tiles-definitions PUBLIC
          "-//Apache Software Foundation//DTD Tiles Configuration 1.1//EN"
          "http://jakarta.apache.org/struts/dtds/tiles-config_1_1.dtd">

<tiles-definitions>
    <!-- 考试类别 -->
    <definition name="testcatlist" extends="bizDef">
		<put name="body" value="/WEB-INF/pages/manager/testcatList.jsp" />
	</definition>		
	<definition name="testcat" extends="bizDef">
		<put name="body" value="/WEB-INF/pages/manager/testcat.jsp" />
	</definition>	
	<definition name="testcatedit" extends="bizDef">
		<put name="body" value="/WEB-INF/pages/manager/testcatEdit.jsp" />
	</definition>	
	<definition name="testcatview" extends="bizDef">
		<put name="body" value="/WEB-INF/pages/manager/testcatView.jsp" />
	</definition>
	
	<!-- 考试 -->
    <definition name="testlist" extends="bizDef">
		<put name="body" value="/WEB-INF/pages/manager/testList.jsp" />
	</definition>		
	<definition name="test" extends="bizDef">
		<put name="body" value="/WEB-INF/pages/manager/test.jsp" />
	</definition>	
	<definition name="testedit" extends="bizDef">
		<put name="body" value="/WEB-INF/pages/manager/testEdit.jsp" />
	</definition>	
	<definition name="testview" extends="bizDef">
		<put name="body" value="/WEB-INF/pages/manager/testView.jsp" />
	</definition>

    <!-- 考生数据导入 -->
    <definition name="selfile" extends="bizDef">
		<put name="body" value="/WEB-INF/pages/manager/selfile.jsp" />
	</definition>
	<definition name="importsuccess" extends="bizDef">
		<put name="body" value="/WEB-INF/pages/manager/importsuccess.jsp" />
	</definition>
	<definition name="importfail" extends="bizDef">
		<put name="body" value="/WEB-INF/pages/manager/importfail.jsp" />
	</definition>
	
	<!-- 考生成绩导入 -->
    <definition name="gradesselfile" extends="bizDef">
		<put name="body" value="/WEB-INF/pages/manager/gradesselfile.jsp" />
	</definition>
	<definition name="gradesimportsuccess" extends="bizDef">
		<put name="body" value="/WEB-INF/pages/manager/gradesimportsuccess.jsp" />
	</definition>
	<definition name="gradesimportfail" extends="bizDef">
		<put name="body" value="/WEB-INF/pages/manager/gradesimportfail.jsp" />
	</definition>
	
	 <!-- 缴费考试修改 -->
	<definition name="feeTestUpdateQuery" extends="bizDef">
		<put name="body" value="/WEB-INF/pages/manager/feeTestUpdateQuery.jsp" />
	</definition>
    
    <!-- 考生数据维护 -->
     <definition name="studentedit" extends="bizDef">
		<put name="body" value="/WEB-INF/pages/manager/studentEdit.jsp" />
	</definition>	
    <definition name="stutestlist" extends="bizDef">
		<put name="body" value="/WEB-INF/pages/manager/stutestList.jsp" />
	</definition>		
	<definition name="stutest" extends="bizDef">
		<put name="body" value="/WEB-INF/pages/manager/stutest.jsp" />
	</definition>
	<definition name="stutestadd" extends="bizDef">
		<put name="body" value="/WEB-INF/pages/manager/stutestAdd.jsp" />
	</definition>
	<definition name="stutestedit" extends="bizDef">
		<put name="body" value="/WEB-INF/pages/manager/stutestEdit.jsp" />
	</definition>	
	<definition name="stutesteditbm" extends="bizDef">
		<put name="body" value="/WEB-INF/pages/manager/stutestEditBm.jsp" />
	</definition>
	<definition name="stutesteditnone" extends="bizDef">
		<put name="body" value="/WEB-INF/pages/manager/stutestEditNone.jsp" />
	</definition>
	<definition name="stutesttongji" extends="bizDef">
		<put name="body" value="/WEB-INF/pages/manager/stutestTJ.jsp" />
	</definition>
	
	<definition name="historylist" extends="bizDef">
		<put name="body" value="/WEB-INF/pages/manager/historyList.jsp" />
	</definition>
	
	<!-- 考试发布信息 -->
    <definition name="testpublishlist" extends="bizDef">
		<put name="body" value="/WEB-INF/pages/manager/testpublishList.jsp" />
	</definition>		
	<definition name="testpublish" extends="bizDef">
		<put name="body" value="/WEB-INF/pages/manager/testpublish.jsp" />
	</definition>	
	<definition name="testpublishedit" extends="bizDef">
		<put name="body" value="/WEB-INF/pages/manager/testpublishEdit.jsp" />
	</definition>	
	<definition name="testpublishview" extends="bizDef">
		<put name="body" value="/WEB-INF/pages/manager/testpublishView.jsp" />
	</definition>	
	<definition name="testpublishlistview" extends="bizDef">
		<put name="body" value="/WEB-INF/pages/manager/testpublishListview.jsp" />
	</definition>
	<definition name="testpublishstuview" extends="bizDef">
		<put name="body" value="/WEB-INF/pages/manager/testpublishstuView.jsp" />
	</definition>
	
	<definition name="picUploadnoFile" extends="bizDef">
		<put name="body" value="/WEB-INF/pages/picuploadsuccess.jsp" />
	</definition>
	<definition name="picUploadfail" extends="bizDef">
		<put name="body" value="/WEB-INF/pages/picuploadfail.jsp" />
	</definition>
	
	<definition name="loginedit" extends="bizDef">
		<put name="body" value="/WEB-INF/pages/manager/loginnotice.jsp" />
	</definition>
		
	<definition name="pubsuccess" extends="bizDef">
		<put name="body" value="/WEB-INF/pages/manager/testpublishListpubview.jsp" />
	</definition>
	<definition name="pubview" extends="bizDef">
		<put name="body" value="/WEB-INF/pages/manager/testpublishstupubView.jsp" />
	</definition>
	

   	<definition name="timeout" extends="bizDef">
		<put name="body" value="/WEB-INF/pages/timeout.jsp" />
	</definition>
</tiles-definitions>