<?xml version="1.0" encoding="utf-8"?>
<!DOCTYPE hibernate-mapping PUBLIC "-//Hibernate/Hibernate Mapping DTD 3.0//EN"
"http://hibernate.sourceforge.net/hibernate-mapping-3.0.dtd">
<!-- 
    Mapping file autogenerated by MyEclipse Persistence Tools
-->
<hibernate-mapping>
    <class name="com.kingstargroup.fdykt.newform.StoreLimit" table="STORE_LIMIT" schema="YKT_PORTAL">
        <composite-id name="id" class="com.kingstargroup.fdykt.newform.StoreLimitId">
            <key-property name="operCode" type="java.lang.String">
                <column name="OPER_CODE" length="60" />
            </key-property>
            <key-property name="storeCode" type="java.lang.String">
                <column name="STORE_CODE" length="6" />
            </key-property>
        </composite-id>
    </class>
</hibernate-mapping>
